README.md
setup.cfg
setup.py
email2country/__init__.py
email2country/email2country.py
email2country/utils.py
email2country.egg-info/PKG-INFO
email2country.egg-info/SOURCES.txt
email2country.egg-info/dependency_links.txt
email2country.egg-info/requires.txt
email2country.egg-info/top_level.txt