Metadata-Version: 2.1
Name: email2country
Version: 0.1.0
Summary: A package to look up the country of email addresses and domains
Home-page: https://github.com/zhijing-jin/email2country
Author: Zhijing Jin
Author-email: zhijing.jin@connect.hku.hk
License: MIT
Platform: UNKNOWN
